smog/__init__.py
smog/__main__.py
smog/colname.py
smog/const.py
smog/context.py
smog/ctxflow.py
smog/dbconf.py
smog/dbmedia.py
smog/dbschema.py
smog/examine.py
smog/file.py
smog/file1name.py
smog/gps.py
smog/memo.py
smog/organize.py
smog/smog.py
smog/timeguess.py
smog/xmpex.py
smog/xmptype.py
smog_alembic/__init__.py
smog_alembic/env.py
smog_alembic/versions/4f47b5e0d6b8_initial.py
smog_alembic/versions/__init__.py
smogconvert/__init__.py
smogconvert/__main__.py
smogconvert/conv2jpeg.py
smogconvert/copyfile.py
smogconvert/pdfwatermark.py
smogconvert/penv.py
smogconvert/resize.py
smogconvert/smogmedia.py
smogconvert/strip.py
smogconvert/thumbnail.py
smogconvert/watermark.py
smogconvert/xmpget.py
smogconvert/xmpset.py
smogconvert/core/__init__.py
smogconvert/core/adapter.py
smogconvert/core/convert.py
smogconvert/core/ctxenv.py
smogconvert/core/ctxtempfile.py
smogconvert/core/loader.py
smogconvert/core/sysutil.py
smogconvert/core/xmpex.py
smog-0.0.4.dist-info/LICENSE.md
smog-0.0.4.dist-info/METADATA
smog-0.0.4.dist-info/WHEEL
smog-0.0.4.dist-info/entry_points.txt
smog-0.0.4.dist-info/top_level.txt
smog-0.0.4.dist-info/RECORD
