Metadata-Version: 2.1
Name: smog
Version: 0.0.4
Summary: simple media organizer
Home-page: https://github.com/kr-g/smog
Author: k. goger
Author-email: k.r.goger+smog@gmail.com
License: AGPLv3+
Project-URL: Issues, https://github.com/kr-g/smog/issues
Keywords: media,organizer,pictures,videos,documents,xmp,memo,note,gps
Classifier: Development Status :: 3 - Alpha
Classifier: Operating System :: POSIX :: Linux
Classifier: Operating System :: OS Independent
Classifier: Environment :: Console
Classifier: Topic :: Utilities
Classifier: Topic :: Multimedia
Classifier: Topic :: Communications
Classifier: Topic :: Database
Classifier: Topic :: Documentation
Classifier: Topic :: Office/Business :: News/Diary
Classifier: Topic :: Software Development :: Libraries :: Python Modules
Classifier: Intended Audience :: Developers
Classifier: Intended Audience :: End Users/Desktop
Classifier: Intended Audience :: Information Technology
Classifier: Intended Audience :: Other Audience
Classifier: Programming Language :: Python :: 3
Classifier: License :: Free For Home Use
Classifier: License :: Free for non-commercial use
Classifier: License :: Free To Use But Restricted
Classifier: License :: OSI Approved :: GNU Affero General Public License v3 or later (AGPLv3+)
Classifier: License :: Freely Distributable
Requires-Python: >=3.8
License-File: LICENSE.md
Requires-Dist: SQLAlchemy (>=1.4.40)
Requires-Dist: alembic (>=1.8.1)
Requires-Dist: python-xmp-toolkit (>=2.0.1)
Requires-Dist: python-dateutil (>=2.8.2)
Requires-Dist: PyPDF2 (>=2.10.0)
Requires-Dist: reportlab (>=3.6.11)
